README
babscript.py
babtools_EXAMPLE.py
setup.py
babtools_EXAMPLE.egg-info/PKG-INFO
babtools_EXAMPLE.egg-info/SOURCES.txt
babtools_EXAMPLE.egg-info/dependency_links.txt
babtools_EXAMPLE.egg-info/top_level.txt