Metadata-Version: 1.0
Name: babtools-EXAMPLE
Version: 0.9
Summary: ['Example structure with efficient PyPI usage: very small overhead for updating the PyPI entry.']
Home-page: http://freehg.org/u/ArneBab/babtools_EXAMPLE
Author: Arne Babenhauserheide
Author-email: arne_bab@web.de
License: GNU GPL-3 or later
Keywords: babtools
Platform: any
Classifier: License :: OSI Approved :: GNU General Public License (GPL)
Classifier: Programming Language :: Python
Classifier: Operating System :: OS Independent
Classifier: Topic :: Software Development :: Libraries :: Python Modules
Classifier: Intended Audience :: Developers
Classifier: Intended Audience :: End Users/Desktop
Classifier: Environment :: Console
Classifier: Development Status :: 3 - Alpha
